things_mcp/__init__.py
things_mcp/__main__.py
things_mcp/config.py
things_mcp/context_manager.py
things_mcp/locale_aware_dates.py
things_mcp/main.py
things_mcp/move_operations.py
things_mcp/operation_queue.py
things_mcp/parameter_validator.py
things_mcp/pure_applescript_scheduler.py
things_mcp/reliable_scheduling.py
things_mcp/response_optimizer.py
things_mcp/server.py
things_mcp/shared_cache.py
things_mcp/tools.py
things_mcp/models/__init__.py
things_mcp/models/response_models.py
things_mcp/models/things_models.py
things_mcp/scheduling/__init__.py
things_mcp/scheduling/helpers.py
things_mcp/scheduling/search.py
things_mcp/scheduling/strategies.py
things_mcp/scheduling/todo_operations.py
things_mcp/services/__init__.py
things_mcp/services/applescript_manager.py
things_mcp/services/cache_manager.py
things_mcp/services/error_handler.py
things_mcp/services/tag_service.py
things_mcp/services/validation_service.py
things_mcp/services/applescript/__init__.py
things_mcp/services/applescript/executor.py
things_mcp/services/applescript/formatters.py
things_mcp/services/applescript/parser.py
things_mcp/services/applescript/queries.py
things_mcp/tools_helpers/__init__.py
things_mcp/tools_helpers/bulk_operations.py
things_mcp/tools_helpers/helpers.py
things_mcp/tools_helpers/read_operations.py
things_mcp/tools_helpers/write_operations.py
things_mcp/utils/__init__.py
things_mcp/utils/applescript_utils.py
mcp_server_things-1.3.2.dist-info/LICENSE
mcp_server_things-1.3.2.dist-info/METADATA
mcp_server_things-1.3.2.dist-info/WHEEL
mcp_server_things-1.3.2.dist-info/entry_points.txt
mcp_server_things-1.3.2.dist-info/top_level.txt
mcp_server_things-1.3.2.dist-info/RECORD
